trytond/modules/account_de_skr04/LICENSE
trytond/modules/account_de_skr04/README.rst
trytond/modules/account_de_skr04/__init__.py
trytond/modules/account_de_skr04/account_template.xml
trytond/modules/account_de_skr04/account_type_template.xml
trytond/modules/account_de_skr04/tax_code_line_template.xml
trytond/modules/account_de_skr04/tax_code_template.xml
trytond/modules/account_de_skr04/tax_group.xml
trytond/modules/account_de_skr04/tax_rule_line_template.xml
trytond/modules/account_de_skr04/tax_rule_template.xml
trytond/modules/account_de_skr04/tax_template.xml
trytond/modules/account_de_skr04/tryton.cfg
mds_account_de_skr04-7.0.9.dist-info/LICENSE
mds_account_de_skr04-7.0.9.dist-info/METADATA
mds_account_de_skr04-7.0.9.dist-info/WHEEL
mds_account_de_skr04-7.0.9.dist-info/entry_points.txt
mds_account_de_skr04-7.0.9.dist-info/top_level.txt
mds_account_de_skr04-7.0.9.dist-info/RECORD
