Metadata-Version: 2.1
Name: mds-account-de-skr04
Version: 7.0.9
Summary: Tryton module with German chart of accounts SKR04
Home-page: https://www.m-ds.de/
Author: m-ds GmbH
Author-email: service@m-ds.de
License: GPL-3
Keywords: tryton account chart german SKR04
Platform: UNKNOWN
Classifier: Development Status :: 5 - Production/Stable
Classifier: Environment :: Plugins
Classifier: Framework :: Tryton
Classifier: Intended Audience :: Developers
Classifier: Intended Audience :: Customer Service
Classifier: Intended Audience :: Information Technology
Classifier: Intended Audience :: Financial and Insurance Industry
Classifier: Intended Audience :: Legal Industry
Classifier: Topic :: Office/Business :: Financial :: Accounting
Classifier: Natural Language :: German
Classifier: Operating System :: OS Independent
Classifier: License :: OSI Approved :: GNU General Public License (GPL)
Classifier: Programming Language :: Python :: 3.7
Classifier: Programming Language :: Python :: 3.8
Classifier: Programming Language :: Python :: 3.9
Requires-Dist: trytond (<7.1,>=7.0)
Requires-Dist: trytond-account (<7.1,>=7.0)
